flask_webtest.py
Flask_WebTest-0.1.6.dist-info/LICENSE
Flask_WebTest-0.1.6.dist-info/METADATA
Flask_WebTest-0.1.6.dist-info/WHEEL
Flask_WebTest-0.1.6.dist-info/top_level.txt
Flask_WebTest-0.1.6.dist-info/RECORD
