Metadata-Version: 2.1
Name: Flask-WebTest
Version: 0.1.6
Summary: Utilities for testing Flask applications with WebTest.
Home-page: https://github.com/level12/flask-webtest
Author: Anton Romanovich
Author-email: anthony.romanovich@gmail.com
License: BSD
Classifier: Topic :: Software Development :: Testing
Classifier: Environment :: Web Environment
Classifier: Intended Audience :: Developers
Classifier: Programming Language :: Python :: 3
License-File: LICENSE
Requires-Dist: Flask >=1.1.0
Requires-Dist: WebTest
Requires-Dist: blinker
Provides-Extra: tests
Requires-Dist: flask-sqlalchemy ; extra == 'tests'
Requires-Dist: greenlet ; extra == 'tests'
